Metadata-Version: 2.1
Name: mpyc
Version: 0.10
Summary: MPyC for Multiparty Computation in Python
Home-page: https://github.com/lschoe/mpyc
Author: Berry Schoenmakers
Author-email: berry@win.tue.nl
License: MIT License
Keywords: crypto,cryptography,multiparty computation,MPC,secret sharing,Shamir threshold scheme,pseudorandom secret sharing,PRSS
Platform: any
Classifier: Development Status :: 4 - Beta
Classifier: Environment :: Console
Classifier: Framework :: AsyncIO
Classifier: Framework :: Jupyter
Classifier: Intended Audience :: Developers
Classifier: Intended Audience :: Education
Classifier: Intended Audience :: Information Technology
Classifier: Intended Audience :: Science/Research
Classifier: License :: OSI Approved :: MIT License
Classifier: Operating System :: OS Independent
Classifier: Programming Language :: Python :: 3 :: Only
Classifier: Topic :: Security :: Cryptography
Classifier: Topic :: Software Development :: Libraries :: Application Frameworks
Classifier: Topic :: Software Development :: Libraries :: Python Modules
Classifier: Topic :: System :: Distributed Computing
Requires-Python: >=3.9
License-File: LICENSE
